indexify_text_splitters-0.1.0.dist-info/METADATA
indexify_text_splitters-0.1.0.dist-info/WHEEL
indexify_text_splitters/__init__.py
indexify_text_splitters/recursive_text_splitter.py
indexify_text_splitters/indexify_text_splitters.cpython-311-darwin.so
indexify_text_splitters-0.1.0.dist-info/RECORD
